setup.py
nsi.cloudooomanager.egg-info/PKG-INFO
nsi.cloudooomanager.egg-info/SOURCES.txt
nsi.cloudooomanager.egg-info/dependency_links.txt
nsi.cloudooomanager.egg-info/entry_points.txt
nsi.cloudooomanager.egg-info/requires.txt
nsi.cloudooomanager.egg-info/top_level.txt
nsi.cloudooomanager.egg-info/zip-safe
nsicloudooomanager/__init__.py
nsicloudooomanager/auth.py
nsicloudooomanager/http.py
nsicloudooomanager/tasks.py
nsicloudooomanager/interfaces/__init__.py
nsicloudooomanager/interfaces/auth.py
nsicloudooomanager/interfaces/http.py