Metadata-Version: 1.0
Name: nsi.cloudooomanager
Version: 0.2.5
Summary: A package to intercept all calls to a CloudOOO Server.
Home-page: UNKNOWN
Author: Douglas Camata
Author-email: d.camata@gmail.com
License: GPL
Platform: UNKNOWN
